Compiled from "Atm.java"
class Atm extends javax.swing.JFrame implements java.awt.event.ActionListener,java.awt.event.MouseListener {
  javax.swing.JPanel enquiry;

  javax.swing.JPanel options;

  javax.swing.JPanel fastpanel;

  javax.swing.JPanel withdrawal;

  javax.swing.JPanel withdrawal1;

  javax.swing.JPanel depositpanel;

  javax.swing.JPanel transferpanel;

  javax.swing.JPanel transferpanel1;

  javax.swing.JPanel ministatement;

  javax.swing.JPanel exit;

  static int z;

  java.lang.String k;

  java.lang.String q;

  static int wd;

  static int keystate;

  static int cnt1;

  static int cnt2;

  static int cnt3;

  static int cnt4;

  static int cnt5;

  static int cnt6;

  java.lang.String user;

  int usr;

  int pass;

  int cnt;

  int accno;

  int tacc;

  int tamt;

  int deposi;

  javax.swing.JLabel msg1;

  javax.swing.JLabel fast;

  javax.swing.JLabel balance;

  javax.swing.JLabel cash;

  javax.swing.JLabel deposit;

  javax.swing.JLabel mini;

  javax.swing.JLabel transfer;

  javax.swing.JPanel pan1;

  javax.swing.JPanel pan0;

  javax.swing.JPanel pantop;

  javax.swing.JPanel panmiddle;

  javax.swing.JPanel loginpanel;

  javax.swing.JPanel mainpanel;

  javax.swing.JPanel accountpanel;

  javax.swing.JPanel adpanel;

  javax.swing.JButton b1;

  javax.swing.JButton b2;

  javax.swing.JButton b3;

  javax.swing.JButton b4;

  javax.swing.JButton b5;

  javax.swing.JButton b6;

  javax.swing.JButton b7;

  javax.swing.JButton b8;

  javax.swing.JButton b9;

  javax.swing.JButton b0;

  javax.swing.JButton bclear;

  javax.swing.JButton bcancel;

  javax.swing.JButton bok;

  javax.swing.JButton but1;

  javax.swing.JButton but2;

  javax.swing.JButton but3;

  javax.swing.JButton but4;

  javax.swing.JButton but5;

  javax.swing.JButton but6;

  javax.swing.JButton but7;

  javax.swing.JButton but8;

  javax.swing.JButton but9;

  javax.swing.JTextField loginfield;

  javax.swing.JTextField textamt;

  javax.swing.JTextField textamt1;

  javax.swing.JTextArea textarea;

  java.awt.CardLayout cardlay;

  java.awt.CardLayout cardlay1;

  java.awt.Container c;

  javax.swing.JLabel labb;

  javax.swing.JLabel label;

  javax.swing.JLabel label2;

  javax.swing.JLabel label3;

  javax.swing.JLabel label4;

  javax.swing.JLabel label4a;

  javax.swing.JLabel label5;

  javax.swing.JLabel label6;

  javax.swing.JLabel label6a;

  javax.swing.JLabel label7;

  java.awt.BorderLayout blo;

  java.awt.Color c1;

  java.awt.Color c2;

  Atm$OptionButtonHandler handler;

  Atm();
    Code:
       0: aload_0
       1: invokespecial #1                  // Method javax/swing/JFrame."<init>":()V
       4: aload_0
       5: ldc           #2                  // String
       7: putfield      #3                  // Field k:Ljava/lang/String;
      10: aload_0
      11: ldc           #2                  // String
      13: putfield      #4                  // Field q:Ljava/lang/String;
      16: aload_0
      17: iconst_2
      18: putfield      #5                  // Field cnt:I
      21: aload_0
      22: new           #6                  // class Atm$OptionButtonHandler
      25: dup
      26: aload_0
      27: aconst_null
      28: invokespecial #7                  // Method Atm$OptionButtonHandler."<init>":(LAtm;LAtm$1;)V
      31: putfield      #8                  // Field handler:LAtm$OptionButtonHandler;
      34: return

  public void Atmmain();
    Code:
       0: aload_0
       1: invokevirtual #9                  // Method getContentPane:()Ljava/awt/Container;
       4: astore_1
       5: aload_0
       6: invokevirtual #9                  // Method getContentPane:()Ljava/awt/Container;
       9: astore_1
      10: aload_1
      11: aconst_null
      12: invokevirtual #10                 // Method java/awt/Container.setLayout:(Ljava/awt/LayoutManager;)V
      15: aload_0
      16: new           #11                 // class javax/swing/JButton
      19: dup
      20: ldc           #12                 // String >>>
      22: invokespecial #13                 // Method javax/swing/JButton."<init>":(Ljava/lang/String;)V
      25: putfield      #14                 // Field but1:Ljavax/swing/JButton;
      28: aload_0
      29: getfield      #14                 // Field but1:Ljavax/swing/JButton;
      32: new           #15                 // class java/awt/Dimension
      35: dup
      36: bipush        100
      38: bipush        30
      40: invokespecial #16                 // Method java/awt/Dimension."<init>":(II)V
      43: invokevirtual #17                 // Method javax/swing/JButton.setPreferredSize:(Ljava/awt/Dimension;)V
      46: aload_0
      47: getfield      #14                 // Field but1:Ljavax/swing/JButton;
      50: aload_0
      51: getfield      #14                 // Field but1:Ljavax/swing/JButton;
      54: invokevirtual #18                 // Method javax/swing/JButton.getPreferredSize:()Ljava/awt/Dimension;
      57: invokevirtual #19                 // Method javax/swing/JButton.setSize:(Ljava/awt/Dimension;)V
      60: aload_0
      61: getfield      #14                 // Field but1:Ljavax/swing/JButton;
      64: bipush        50
      66: bipush        50
      68: invokevirtual #20                 // Method javax/swing/JButton.setLocation:(II)V
      71: aload_1
      72: aload_0
      73: getfield      #14                 // Field but1:Ljavax/swing/JButton;
      76: invokevirtual #21                 // Method java/awt/Container.add:(Ljava/awt/Component;)Ljava/awt/Component;
      79: pop
      80: aload_0
      81: new           #11                 // class javax/swing/JButton
      84: dup
      85: ldc           #12                 // String >>>
      87: invokespecial #13                 // Method javax/swing/JButton."<init>":(Ljava/lang/String;)V
      90: putfield      #22                 // Field but2:Ljavax/swing/JButton;
      93: aload_0
      94: getfield      #22                 // Field but2:Ljavax/swing/JButton;
      97: new           #15                 // class java/awt/Dimension
     100: dup
     101: bipush        100
     103: bipush        30
     105: invokespecial #16                 // Method java/awt/Dimension."<init>":(II)V
     108: invokevirtual #17                 // Method javax/swing/JButton.setPreferredSize:(Ljava/awt/Dimension;)V
     111: aload_0
     112: getfield      #22                 // Field but2:Ljavax/swing/JButton;
     115: aload_0
     116: getfield      #22                 // Field but2:Ljavax/swing/JButton;
     119: invokevirtual #18                 // Method javax/swing/JButton.getPreferredSize:()Ljava/awt/Dimension;
     122: invokevirtual #19                 // Method javax/swing/JButton.setSize:(Ljava/awt/Dimension;)V
     125: aload_0
     126: getfield      #22                 // Field but2:Ljavax/swing/JButton;
     129: bipush        50
     131: bipush        100
     133: invokevirtual #20                 // Method javax/swing/JButton.setLocation:(II)V
     136: aload_1
     137: aload_0
     138: getfield      #22                 // Field but2:Ljavax/swing/JButton;
     141: invokevirtual #21                 // Method java/awt/Container.add:(Ljava/awt/Component;)Ljava/awt/Component;
     144: pop
     145: aload_0
     146: new           #11                 // class javax/swing/JButton
     149: dup
     150: ldc           #12                 // String >>>
     152: invokespecial #13                 // Method javax/swing/JButton."<init>":(Ljava/lang/String;)V
     155: putfield      #23                 // Field but3:Ljavax/swing/JButton;
     158: aload_0
     159: getfield      #23                 // Field but3:Ljavax/swing/JButton;
     162: new           #15                 // class java/awt/Dimension
     165: dup
     166: bipush        100
     168: bipush        30
     170: invokespecial #16                 // Method java/awt/Dimension."<init>":(II)V
     173: invokevirtual #17                 // Method javax/swing/JButton.setPreferredSize:(Ljava/awt/Dimension;)V
     176: aload_0
     177: getfield      #23                 // Field but3:Ljavax/swing/JButton;
     180: aload_0
     181: getfield      #23                 // Field but3:Ljavax/swing/JButton;
     184: invokevirtual #18                 // Method javax/swing/JButton.getPreferredSize:()Ljava/awt/Dimension;
     187: invokevirtual #19                 // Method javax/swing/JButton.setSize:(Ljava/awt/Dimension;)V
     190: aload_0
     191: getfield      #23                 // Field but3:Ljavax/swing/JButton;
     194: bipush        50
     196: sipush        150
     199: invokevirtual #20                 // Method javax/swing/JButton.setLocation:(II)V
     202: aload_1
     203: aload_0
     204: getfield      #23                 // Field but3:Ljavax/swing/JButton;
     207: invokevirtual #21                 // Method java/awt/Container.add:(Ljava/awt/Component;)Ljava/awt/Component;
     210: pop
     211: aload_0
     212: new           #11                 // class javax/swing/JButton
     215: dup
     216: ldc           #24                 // String <<<
     218: invokespecial #13                 // Method javax/swing/JButton."<init>":(Ljava/lang/String;)V
     221: putfield      #25                 // Field but4:Ljavax/swing/JButton;
     224: aload_0
     225: getfield      #25                 // Field but4:Ljavax/swing/JButton;
     228: new           #15                 // class java/awt/Dimension
     231: dup
     232: bipush        100
     234: bipush        30
     236: invokespecial #16                 // Method java/awt/Dimension."<init>":(II)V
     239: invokevirtual #17                 // Method javax/swing/JButton.setPreferredSize:(Ljava/awt/Dimension;)V
     242: aload_0
     243: getfield      #25                 // Field but4:Ljavax/swing/JButton;
     246: aload_0
     247: getfield      #25                 // Field but4:Ljavax/swing/JButton;
     250: invokevirtual #18                 // Method javax/swing/JButton.getPreferredSize:()Ljava/awt/Dimension;
     253: invokevirtual #19                 // Method javax/swing/JButton.setSize:(Ljava/awt/Dimension;)V
     256: aload_0
     257: getfield      #25                 // Field but4:Ljavax/swing/JButton;
     260: sipush        575
     263: bipush        50
     265: invokevirtual #20                 // Method javax/swing/JButton.setLocation:(II)V
     268: aload_1
     269: aload_0
     270: getfield      #25                 // Field but4:Ljavax/swing/JButton;
     273: invokevirtual #21                 // Method java/awt/Container.add:(Ljava/awt/Component;)Ljava/awt/Component;
     276: pop
     277: aload_0
     278: new           #11                 // class javax/swing/JButton
     281: dup
     282: ldc           #24                 // String <<<
     284: invokespecial #13                 // Method javax/swing/JButton."<init>":(Ljava/lang/String;)V
     287: putfield      #26                 // Field but5:Ljavax/swing/JButton;
     290: aload_0
     291: getfield      #26                 // Field but5:Ljavax/swing/JButton;
     294: new           #15                 // class java/awt/Dimension
     297: dup
     298: bipush        100
     300: bipush        30
     302: invokespecial #16                 // Method java/awt/Dimension."<init>":(II)V
     305: invokevirtual #17                 // Method javax/swing/JButton.setPreferredSize:(Ljava/awt/Dimension;)V
     308: aload_0
     309: getfield      #26                 // Field but5:Ljavax/swing/JButton;
     312: aload_0
     313: getfield      #26                 // Field but5:Ljavax/swing/JButton;
     316: invokevirtual #18                 // Method javax/swing/JButton.getPreferredSize:()Ljava/awt/Dimension;
     319: invokevirtual #19                 // Method javax/swing/JButton.setSize:(Ljava/awt/Dimension;)V
     322: aload_0
     323: getfield      #26                 // Field but5:Ljavax/swing/JButton;
     326: sipush        575
     329: bipush        100
     331: invokevirtual #20                 // Method javax/swing/JButton.setLocation:(II)V
     334: aload_1
     335: aload_0
     336: getfield      #26                 // Field but5:Ljavax/swing/JButton;
     339: invokevirtual #21                 // Method java/awt/Container.add:(Ljava/awt/Component;)Ljava/awt/Component;
     342: pop
     343: aload_0
     344: new           #11                 // class javax/swing/JButton
     347: dup
     348: ldc           #24                 // String <<<
     350: invokespecial #13                 // Method javax/swing/JButton."<init>":(Ljava/lang/String;)V
     353: putfield      #27                 // Field but6:Ljavax/swing/JButton;
     356: aload_0
     357: getfield      #27                 // Field but6:Ljavax/swing/JButton;
     360: new           #15                 // class java/awt/Dimension
     363: dup
     364: bipush        100
     366: bipush        30
     368: invokespecial #16                 // Method java/awt/Dimension."<init>":(II)V
     371: invokevirtual #17                 // Method javax/swing/JButton.setPreferredSize:(Ljava/awt/Dimension;)V
     374: aload_0
     375: getfield      #27                 // Field but6:Ljavax/swing/JButton;
     378: aload_0
     379: getfield      #27                 // Field but6:Ljavax/swing/JButton;
     382: invokevirtual #18                 // Method javax/swing/JButton.getPreferredSize:()Ljava/awt/Dimension;
     385: invokevirtual #19                 // Method javax/swing/JButton.setSize:(Ljava/awt/Dimension;)V
     388: aload_0
     389: getfield      #27                 // Field but6:Ljavax/swing/JButton;
     392: sipush        575
     395: sipush        150
     398: invokevirtual #20                 // Method javax/swing/JButton.setLocation:(II)V
     401: aload_1
     402: aload_0
     403: getfield      #27                 // Field but6:Ljavax/swing/JButton;
     406: invokevirtual #21                 // Method java/awt/Container.add:(Ljava/awt/Component;)Ljava/awt/Component;
     409: pop
     410: aload_0
     411: new           #11                 // class javax/swing/JButton
     414: dup
     415: ldc           #28                 // String 1
     417: invokespecial #13                 // Method javax/swing/JButton."<init>":(Ljava/lang/String;)V
     420: putfield      #29                 // Field b1:Ljavax/swing/JButton;
     423: aload_0
     424: new           #11                 // class javax/swing/JButton
     427: dup
     428: ldc           #30                 // String 2
     430: invokespecial #13                 // Method javax/swing/JButton."<init>":(Ljava/lang/String;)V
     433: putfield      #31                 // Field b2:Ljavax/swing/JButton;
     436: aload_0
     437: new           #11                 // class javax/swing/JButton
     440: dup
     441: ldc           #32                 // String 3
     443: invokespecial #13                 // Method javax/swing/JButton."<init>":(Ljava/lang/String;)V
     446: putfield      #33                 // Field b3:Ljavax/swing/JButton;
     449: aload_0
     450: new           #11                 // class javax/swing/JButton
     453: dup
     454: ldc           #34                 // String 4
     456: invokespecial #13                 // Method javax/swing/JButton."<init>":(Ljava/lang/String;)V
     459: putfield      #35                 // Field b4:Ljavax/swing/JButton;
     462: aload_0
     463: new           #11                 // class javax/swing/JButton
     466: dup
     467: ldc           #36                 // String 5
     469: invokespecial #13                 // Method javax/swing/JButton."<init>":(Ljava/lang/String;)V
     472: putfield      #37                 // Field b5:Ljavax/swing/JButton;
     475: aload_0
     476: new           #11                 // class javax/swing/JButton
     479: dup
     480: ldc           #38                 // String 6
     482: invokespecial #13                 // Method javax/swing/JButton."<init>":(Ljava/lang/String;)V
     485: putfield      #39                 // Field b6:Ljavax/swing/JButton;
     488: aload_0
     489: new           #11                 // class javax/swing/JButton
     492: dup
     493: ldc           #40                 // String 7
     495: invokespecial #13                 // Method javax/swing/JButton."<init>":(Ljava/lang/String;)V
     498: putfield      #41                 // Field b7:Ljavax/swing/JButton;
     501: aload_0
     502: new           #11                 // class javax/swing/JButton
     505: dup
     506: ldc           #42                 // String 8
     508: invokespecial #13                 // Method javax/swing/JButton."<init>":(Ljava/lang/String;)V
     511: putfield      #43                 // Field b8:Ljavax/swing/JButton;
     514: aload_0
     515: new           #11                 // class javax/swing/JButton
     518: dup
     519: ldc           #44                 // String 9
     521: invokespecial #13                 // Method javax/swing/JButton."<init>":(Ljava/lang/String;)V
     524: putfield      #45                 // Field b9:Ljavax/swing/JButton;
     527: aload_0
     528: new           #11                 // class javax/swing/JButton
     531: dup
     532: ldc           #46                 // String 0
     534: invokespecial #13                 // Method javax/swing/JButton."<init>":(Ljava/lang/String;)V
     537: putfield      #47                 // Field b0:Ljavax/swing/JButton;
     540: aload_0
     541: new           #11                 // class javax/swing/JButton
     544: dup
     545: ldc           #48                 // String CLEAR
     547: invokespecial #13                 // Method javax/swing/JButton."<init>":(Ljava/lang/String;)V
     550: putfield      #49                 // Field bclear:Ljavax/swing/JButton;
     553: aload_0
     554: new           #11                 // class javax/swing/JButton
     557: dup
     558: ldc           #50                 // String CANCEL
     560: invokespecial #13                 // Method javax/swing/JButton."<init>":(Ljava/lang/String;)V
     563: putfield      #51                 // Field bcancel:Ljavax/swing/JButton;
     566: aload_0
     567: new           #11                 // class javax/swing/JButton
     570: dup
     571: ldc           #52                 // String OK
     573: invokespecial #13                 // Method javax/swing/JButton."<init>":(Ljava/lang/String;)V
     576: putfield      #53                 // Field bok:Ljavax/swing/JButton;
     579: aload_0
     580: new           #54                 // class javax/swing/JPanel
     583: dup
     584: invokespecial #55                 // Method javax/swing/JPanel."<init>":()V
     587: putfield      #56                 // Field pan1:Ljavax/swing/JPanel;
     590: aload_0
     591: getfield      #56                 // Field pan1:Ljavax/swing/JPanel;
     594: new           #57                 // class java/awt/GridLayout
     597: dup
     598: iconst_4
     599: iconst_2
     600: bipush        10
     602: bipush        10
     604: invokespecial #58                 // Method java/awt/GridLayout."<init>":(IIII)V
     607: invokevirtual #59                 // Method javax/swing/JPanel.setLayout:(Ljava/awt/LayoutManager;)V
     610: aload_0
     611: getfield      #56                 // Field pan1:Ljavax/swing/JPanel;
     614: sipush        260
     617: sipush        150
     620: invokevirtual #60                 // Method javax/swing/JPanel.setSize:(II)V
     623: aload_0
     624: getfield      #56                 // Field pan1:Ljavax/swing/JPanel;
     627: aload_0
     628: getfield      #29                 // Field b1:Ljavax/swing/JButton;
     631: invokevirtual #61                 // Method javax/swing/JPanel.add:(Ljava/awt/Component;)Ljava/awt/Component;
     634: pop
     635: aload_0
     636: getfield      #56                 // Field pan1:Ljavax/swing/JPanel;
     639: aload_0
     640: getfield      #31                 // Field b2:Ljavax/swing/JButton;
     643: invokevirtual #61                 // Method javax/swing/JPanel.add:(Ljava/awt/Component;)Ljava/awt/Component;
     646: pop
     647: aload_0
     648: getfield      #56                 // Field pan1:Ljavax/swing/JPanel;
     651: aload_0
     652: getfield      #33                 // Field b3:Ljavax/swing/JButton;
     655: invokevirtual #61                 // Method javax/swing/JPanel.add:(Ljava/awt/Component;)Ljava/awt/Component;
     658: pop
     659: aload_0
     660: getfield      #56                 // Field pan1:Ljavax/swing/JPanel;
     663: aload_0
     664: getfield      #35                 // Field b4:Ljavax/swing/JButton;
     667: invokevirtual #61                 // Method javax/swing/JPanel.add:(Ljava/awt/Component;)Ljava/awt/Component;
     670: pop
     671: aload_0
     672: getfield      #56                 // Field pan1:Ljavax/swing/JPanel;
     675: aload_0
     676: getfield      #37                 // Field b5:Ljavax/swing/JButton;
     679: invokevirtual #61                 // Method javax/swing/JPanel.add:(Ljava/awt/Component;)Ljava/awt/Component;
     682: pop
     683: aload_0
     684: getfield      #56                 // Field pan1:Ljavax/swing/JPanel;
     687: aload_0
     688: getfield      #39                 // Field b6:Ljavax/swing/JButton;
     691: invokevirtual #61                 // Method javax/swing/JPanel.add:(Ljava/awt/Component;)Ljava/awt/Component;
     694: pop
     695: aload_0
     696: getfield      #56                 // Field pan1:Ljavax/swing/JPanel;
     699: aload_0
     700: getfield      #41                 // Field b7:Ljavax/swing/JButton;
     703: invokevirtual #61                 // Method javax/swing/JPanel.add:(Ljava/awt/Component;)Ljava/awt/Component;
     706: pop
     707: aload_0
     708: getfield      #56                 // Field pan1:Ljavax/swing/JPanel;
     711: aload_0
     712: getfield      #43                 // Field b8:Ljavax/swing/JButton;
     715: invokevirtual #61                 // Method javax/swing/JPanel.add:(Ljava/awt/Component;)Ljava/awt/Component;
     718: pop
     719: aload_0
     720: getfield      #56                 // Field pan1:Ljavax/swing/JPanel;
     723: aload_0
     724: getfield      #45                 // Field b9:Ljavax/swing/JButton;
     727: invokevirtual #61                 // Method javax/swing/JPanel.add:(Ljava/awt/Component;)Ljava/awt/Component;
     730: pop
     731: aload_0
     732: getfield      #56                 // Field pan1:Ljavax/swing/JPanel;
     735: aload_0
     736: getfield      #47                 // Field b0:Ljavax/swing/JButton;
     739: invokevirtual #61                 // Method javax/swing/JPanel.add:(Ljava/awt/Component;)Ljava/awt/Component;
     742: pop
     743: aload_0
     744: getfield      #56                 // Field pan1:Ljavax/swing/JPanel;
     747: aload_0
     748: getfield      #49                 // Field bclear:Ljavax/swing/JButton;
     751: invokevirtual #61                 // Method javax/swing/JPanel.add:(Ljava/awt/Component;)Ljava/awt/Component;
     754: pop
     755: aload_0
     756: getfield      #56                 // Field pan1:Ljavax/swing/JPanel;
     759: aload_0
     760: getfield      #51                 // Field bcancel:Ljavax/swing/JButton;
     763: invokevirtual #61                 // Method javax/swing/JPanel.add:(Ljava/awt/Component;)Ljava/awt/Component;
     766: pop
     767: aload_0
     768: getfield      #56                 // Field pan1:Ljavax/swing/JPanel;
     771: sipush        225
     774: sipush        300
     777: invokevirtual #62                 // Method javax/swing/JPanel.setLocation:(II)V
     780: aload_0
     781: getfield      #56                 // Field pan1:Ljavax/swing/JPanel;
     784: getstatic     #63                 // Field java/awt/Color.ORANGE:Ljava/awt/Color;
     787: invokevirtual #64                 // Method javax/swing/JPanel.setBackground:(Ljava/awt/Color;)V
     790: aload_1
     791: aload_0
     792: getfield      #56                 // Field pan1:Ljavax/swing/JPanel;
     795: invokevirtual #21                 // Method java/awt/Container.add:(Ljava/awt/Component;)Ljava/awt/Component;
     798: pop
     799: aload_0
     800: new           #65                 // class java/awt/CardLayout
     803: dup
     804: invokespecial #66                 // Method java/awt/CardLayout."<init>":()V
     807: putfield      #67                 // Field cardlay:Ljava/awt/CardLayout;
     810: aload_0
     811: new           #68                 // class java/awt/BorderLayout
     814: dup
     815: invokespecial #69                 // Method java/awt/BorderLayout."<init>":()V
     818: putfield      #70                 // Field blo:Ljava/awt/BorderLayout;
     821: aload_0
     822: new           #54                 // class javax/swing/JPanel
     825: dup
     826: invokespecial #55                 // Method javax/swing/JPanel."<init>":()V
     829: putfield      #71                 // Field panmiddle:Ljavax/swing/JPanel;
     832: aload_0
     833: getfield      #71                 // Field panmiddle:Ljavax/swing/JPanel;
     836: sipush        402
     839: sipush        250
     842: invokevirtual #60                 // Method javax/swing/JPanel.setSize:(II)V
     845: aload_0
     846: getfield      #71                 // Field panmiddle:Ljavax/swing/JPanel;
     849: sipush        160
     852: bipush        30
     854: invokevirtual #62                 // Method javax/swing/JPanel.setLocation:(II)V
     857: aload_0
     858: getfield      #71                 // Field panmiddle:Ljavax/swing/JPanel;
     861: aload_0
     862: getfield      #67                 // Field cardlay:Ljava/awt/CardLayout;
     865: invokevirtual #59                 // Method javax/swing/JPanel.setLayout:(Ljava/awt/LayoutManager;)V
     868: aload_0
     869: getfield      #71                 // Field panmiddle:Ljavax/swing/JPanel;
     872: getstatic     #72                 // Field java/awt/Color.WHITE:Ljava/awt/Color;
     875: invokevirtual #64                 // Method javax/swing/JPanel.setBackground:(Ljava/awt/Color;)V
     878: aload_0
     879: new           #54                 // class javax/swing/JPanel
     882: dup
     883: invokespecial #55                 // Method javax/swing/JPanel."<init>":()V
     886: putfield      #73                 // Field adpanel:Ljavax/swing/JPanel;
     889: aload_0
     890: new           #54                 // class javax/swing/JPanel
     893: dup
     894: invokespecial #55                 // Method javax/swing/JPanel."<init>":()V
     897: putfield      #74                 // Field loginpanel:Ljavax/swing/JPanel;
     900: aload_0
     901: new           #54                 // class javax/swing/JPanel
     904: dup
     905: invokespecial #55                 // Method javax/swing/JPanel."<init>":()V
     908: putfield      #75                 // Field mainpanel:Ljavax/swing/JPanel;
     911: aload_0
     912: new           #54                 // class javax/swing/JPanel
     915: dup
     916: invokespecial #55                 // Method javax/swing/JPanel."<init>":()V
     919: putfield      #76                 // Field accountpanel:Ljavax/swing/JPanel;
     922: aload_0
     923: getfield      #75                 // Field mainpanel:Ljavax/swing/JPanel;
     926: getstatic     #72                 // Field java/awt/Color.WHITE:Ljava/awt/Color;
     929: invokevirtual #64                 // Method javax/swing/JPanel.setBackground:(Ljava/awt/Color;)V
     932: aload_0
     933: getfield      #71                 // Field panmiddle:Ljavax/swing/JPanel;
     936: aload_0
     937: getfield      #73                 // Field adpanel:Ljavax/swing/JPanel;
     940: ldc           #77                 // String ad
     942: invokevirtual #78                 // Method javax/swing/JPanel.add:(Ljava/awt/Component;Ljava/lang/Object;)V
     945: aload_0
     946: getfield      #71                 // Field panmiddle:Ljavax/swing/JPanel;
     949: aload_0
     950: getfield      #74                 // Field loginpanel:Ljavax/swing/JPanel;
     953: ldc           #79                 // String login
     955: invokevirtual #78                 // Method javax/swing/JPanel.add:(Ljava/awt/Component;Ljava/lang/Object;)V
     958: aload_0
     959: getfield      #71                 // Field panmiddle:Ljavax/swing/JPanel;
     962: aload_0
     963: getfield      #75                 // Field mainpanel:Ljavax/swing/JPanel;
     966: ldc           #80                 // String main
     968: invokevirtual #78                 // Method javax/swing/JPanel.add:(Ljava/awt/Component;Ljava/lang/Object;)V
     971: aload_0
     972: getfield      #71                 // Field panmiddle:Ljavax/swing/JPanel;
     975: aload_0
     976: getfield      #76                 // Field accountpanel:Ljavax/swing/JPanel;
     979: ldc           #81                 // String account
     981: invokevirtual #78                 // Method javax/swing/JPanel.add:(Ljava/awt/Component;Ljava/lang/Object;)V
     984: aload_0
     985: getfield      #73                 // Field adpanel:Ljavax/swing/JPanel;
     988: getstatic     #82                 // Field java/awt/Color.PINK:Ljava/awt/Color;
     991: invokevirtual #64                 // Method javax/swing/JPanel.setBackground:(Ljava/awt/Color;)V
     994: aload_0
     995: invokevirtual #83                 // Method startanimation:()V
     998: aload_1
     999: aload_0
    1000: getfield      #71                 // Field panmiddle:Ljavax/swing/JPanel;
    1003: invokevirtual #21                 // Method java/awt/Container.add:(Ljava/awt/Component;)Ljava/awt/Component;
    1006: pop
    1007: aload_0
    1008: ldc           #84                 // String Main Atm
    1010: invokevirtual #85                 // Method setTitle:(Ljava/lang/String;)V
    1013: aload_0
    1014: sipush        730
    1017: sipush        520
    1020: invokevirtual #86                 // Method setSize:(II)V
    1023: aload_0
    1024: getstatic     #72                 // Field java/awt/Color.WHITE:Ljava/awt/Color;
    1027: invokevirtual #87                 // Method setBackground:(Ljava/awt/Color;)V
    1030: aload_0
    1031: iconst_3
    1032: invokevirtual #88                 // Method setDefaultCloseOperation:(I)V
    1035: aload_0
    1036: iconst_1
    1037: invokevirtual #89                 // Method setVisible:(Z)V
    1040: return

  public void Password();
    Code:
       0: aload_0
       1: getfield      #74                 // Field loginpanel:Ljavax/swing/JPanel;
       4: sipush        200
       7: sipush        200
      10: invokevirtual #60                 // Method javax/swing/JPanel.setSize:(II)V
      13: aload_0
      14: new           #90                 // class java/awt/Color
      17: dup
      18: sipush        255
      21: bipush        100
      23: bipush        100
      25: invokespecial #91                 // Method java/awt/Color."<init>":(III)V
      28: putfield      #92                 // Field c1:Ljava/awt/Color;
      31: aload_0
      32: new           #90                 // class java/awt/Color
      35: dup
      36: sipush        255
      39: bipush        50
      41: bipush        50
      43: invokespecial #91                 // Method java/awt/Color."<init>":(III)V
      46: putfield      #93                 // Field c2:Ljava/awt/Color;
      49: aload_0
      50: getfield      #74                 // Field loginpanel:Ljavax/swing/JPanel;
      53: aload_0
      54: getfield      #92                 // Field c1:Ljava/awt/Color;
      57: invokevirtual #64                 // Method javax/swing/JPanel.setBackground:(Ljava/awt/Color;)V
      60: aload_0
      61: getfield      #74                 // Field loginpanel:Ljavax/swing/JPanel;
      64: aload_0
      65: getfield      #70                 // Field blo:Ljava/awt/BorderLayout;
      68: invokevirtual #59                 // Method javax/swing/JPanel.setLayout:(Ljava/awt/LayoutManager;)V
      71: new           #54                 // class javax/swing/JPanel
      74: dup
      75: invokespecial #55                 // Method javax/swing/JPanel."<init>":()V
      78: astore_1
      79: aload_1
      80: new           #57                 // class java/awt/GridLayout
      83: dup
      84: iconst_3
      85: iconst_2
      86: bipush        10
      88: bipush        10
      90: invokespecial #58                 // Method java/awt/GridLayout."<init>":(IIII)V
      93: invokevirtual #59                 // Method javax/swing/JPanel.setLayout:(Ljava/awt/LayoutManager;)V
      96: aload_1
      97: bipush        100
      99: bipush        50
     101: invokevirtual #60                 // Method javax/swing/JPanel.setSize:(II)V
     104: aload_1
     105: aload_0
     106: getfield      #93                 // Field c2:Ljava/awt/Color;
     109: invokevirtual #64                 // Method javax/swing/JPanel.setBackground:(Ljava/awt/Color;)V
     112: ldc           #94                 // String                      \tW E L C O M E!   \n              \tPlease write your login and password:\n         \t -------------------------------------------\n
     114: astore_2
     115: new           #95                 // class javax/swing/JTextArea
     118: dup
     119: aload_2
     120: invokespecial #96                 // Method javax/swing/JTextArea."<init>":(Ljava/lang/String;)V
     123: astore_3
     124: aload_3
     125: aload_0
     126: getfield      #92                 // Field c1:Ljava/awt/Color;
     129: invokevirtual #97                 // Method javax/swing/JTextArea.setBackground:(Ljava/awt/Color;)V
     132: aload_3
     133: iconst_0
     134: invokevirtual #98                 // Method javax/swing/JTextArea.setEditable:(Z)V
     137: aload_0
     138: getfield      #74                 // Field loginpanel:Ljavax/swing/JPanel;
     141: aload_3
     142: aload_0
     143: getfield      #70                 // Field blo:Ljava/awt/BorderLayout;
     146: pop
     147: ldc           #99                 // String North
     149: invokevirtual #78                 // Method javax/swing/JPanel.add:(Ljava/awt/Component;Ljava/lang/Object;)V
     152: new           #100                // class javax/swing/JLabel
     155: dup
     156: ldc           #101                // String CUSTOMER ID
     158: invokespecial #102                // Method javax/swing/JLabel."<init>":(Ljava/lang/String;)V
     161: astore        4
     163: new           #100                // class javax/swing/JLabel
     166: dup
     167: ldc           #103                // String PIN CODE
     169: invokespecial #102                // Method javax/swing/JLabel."<init>":(Ljava/lang/String;)V
     172: astore        5
     174: aload_0
     175: new           #104                // class javax/swing/JTextField
     178: dup
     179: iconst_4
     180: invokespecial #105                // Method javax/swing/JTextField."<init>":(I)V
     183: putfield      #106                // Field loginfield:Ljavax/swing/JTextField;
     186: aload_1
     187: aload         4
     189: invokevirtual #61                 // Method javax/swing/JPanel.add:(Ljava/awt/Component;)Ljava/awt/Component;
     192: pop
     193: aload_1
     194: aload_0
     195: getfield      #106                // Field loginfield:Ljavax/swing/JTextField;
     198: invokevirtual #61                 // Method javax/swing/JPanel.add:(Ljava/awt/Component;)Ljava/awt/Component;
     201: pop
     202: aload_1
     203: aload         5
     205: invokevirtual #61                 // Method javax/swing/JPanel.add:(Ljava/awt/Component;)Ljava/awt/Component;
     208: pop
     209: aload_0
     210: new           #107                // class javax/swing/JPasswordField
     213: dup
     214: iconst_4
     215: invokespecial #108                // Method javax/swing/JPasswordField."<init>":(I)V
     218: putfield      #109                // Field pwordfield:Ljavax/swing/JPasswordField;
     221: aload_1
     222: aload_0
     223: getfield      #109                // Field pwordfield:Ljavax/swing/JPasswordField;
     226: invokevirtual #61                 // Method javax/swing/JPanel.add:(Ljava/awt/Component;)Ljava/awt/Component;
     229: pop
     230: aload_0
     231: new           #11                 // class javax/swing/JButton
     234: dup
     235: ldc           #52                 // String OK
     237: invokespecial #13                 // Method javax/swing/JButton."<init>":(Ljava/lang/String;)V
     240: putfield      #110                // Field but8:Ljavax/swing/JButton;
     243: aload_0
     244: getfield      #110                // Field but8:Ljavax/swing/JButton;
     247: new           #15                 // class java/awt/Dimension
     250: dup
     251: bipush        90
     253: bipush        25
     255: invokespecial #16                 // Method java/awt/Dimension."<init>":(II)V
     258: invokevirtual #17                 // Method javax/swing/JButton.setPreferredSize:(Ljava/awt/Dimension;)V
     261: aload_0
     262: getfield      #110                // Field but8:Ljavax/swing/JButton;
     265: aload_0
     266: getfield      #110                // Field but8:Ljavax/swing/JButton;
     269: invokevirtual #18                 // Method javax/swing/JButton.getPreferredSize:()Ljava/awt/Dimension;
     272: invokevirtual #19                 // Method javax/swing/JButton.setSize:(Ljava/awt/Dimension;)V
     275: aload_1
     276: aload_0
     277: getfield      #110                // Field but8:Ljavax/swing/JButton;
     280: invokevirtual #61                 // Method javax/swing/JPanel.add:(Ljava/awt/Component;)Ljava/awt/Component;
     283: pop
     284: aload_0
     285: new           #11                 // class javax/swing/JButton
     288: dup
     289: ldc           #50                 // String CANCEL
     291: invokespecial #13                 // Method javax/swing/JButton."<init>":(Ljava/lang/String;)V
     294: putfield      #111                // Field but9:Ljavax/swing/JButton;
     297: aload_0
     298: getfield      #111                // Field but9:Ljavax/swing/JButton;
     301: new           #15                 // class java/awt/Dimension
     304: dup
     305: bipush        90
     307: bipush        25
     309: invokespecial #16                 // Method java/awt/Dimension."<init>":(II)V
     312: invokevirtual #17                 // Method javax/swing/JButton.setPreferredSize:(Ljava/awt/Dimension;)V
     315: aload_0
     316: getfield      #111                // Field but9:Ljavax/swing/JButton;
     319: aload_0
     320: getfield      #111                // Field but9:Ljavax/swing/JButton;
     323: invokevirtual #18                 // Method javax/swing/JButton.getPreferredSize:()Ljava/awt/Dimension;
     326: invokevirtual #19                 // Method javax/swing/JButton.setSize:(Ljava/awt/Dimension;)V
     329: aload_1
     330: aload_0
     331: getfield      #111                // Field but9:Ljavax/swing/JButton;
     334: invokevirtual #61                 // Method javax/swing/JPanel.add:(Ljava/awt/Component;)Ljava/awt/Component;
     337: pop
     338: ldc           #112                // String \t----------------------------------------------\n            \tThis product is a\n       \tguarenteed trade mark of\n \t'SYMBIOSIS COMPUTER SYSTEMS INC.\n\t----------------------------------------------\n       \tProducer:  Parthav & Priyanka
     340: astore        6
     342: aload_0
     343: new           #95                 // class javax/swing/JTextArea
     346: dup
     347: aload         6
     349: invokespecial #96                 // Method javax/swing/JTextArea."<init>":(Ljava/lang/String;)V
     352: putfield      #113                // Field textarea:Ljavax/swing/JTextArea;
     355: aload_0
     356: getfield      #74                 // Field loginpanel:Ljavax/swing/JPanel;
     359: aload_0
     360: getfield      #113                // Field textarea:Ljavax/swing/JTextArea;
     363: aload_0
     364: getfield      #70                 // Field blo:Ljava/awt/BorderLayout;
     367: pop
     368: ldc           #114                // String South
     370: invokevirtual #78                 // Method javax/swing/JPanel.add:(Ljava/awt/Component;Ljava/lang/Object;)V
     373: aload_0
     374: getfield      #113                // Field textarea:Ljavax/swing/JTextArea;
     377: aload_0
     378: getfield      #92                 // Field c1:Ljava/awt/Color;
     381: invokevirtual #97                 // Method javax/swing/JTextArea.setBackground:(Ljava/awt/Color;)V
     384: aload_0
     385: getfield      #113                // Field textarea:Ljavax/swing/JTextArea;
     388: iconst_0
     389: invokevirtual #98                 // Method javax/swing/JTextArea.setEditable:(Z)V
     392: aload_0
     393: getfield      #74                 // Field loginpanel:Ljavax/swing/JPanel;
     396: aload_1
     397: aload_0
     398: getfield      #70                 // Field blo:Ljava/awt/BorderLayout;
     401: pop
     402: ldc           #115                // String East
     404: invokevirtual #78                 // Method javax/swing/JPanel.add:(Ljava/awt/Component;Ljava/lang/Object;)V
     407: aload_0
     408: getfield      #106                // Field loginfield:Ljavax/swing/JTextField;
     411: invokevirtual #116                // Method javax/swing/JTextField.requestFocus:()V
     414: aload_0
     415: getfield      #110                // Field but8:Ljavax/swing/JButton;
     418: aload_0
     419: invokevirtual #117                // Method javax/swing/JButton.addActionListener:(Ljava/awt/event/ActionListener;)V
     422: aload_0
     423: getfield      #111                // Field but9:Ljavax/swing/JButton;
     426: aload_0
     427: invokevirtual #117                // Method javax/swing/JButton.addActionListener:(Ljava/awt/event/ActionListener;)V
     430: return

  public void startanimation();
    Code:
       0: new           #118                // class LogoAnimatorJPanel
       3: dup
       4: invokespecial #119                // Method LogoAnimatorJPanel."<init>":()V
       7: astore_1
       8: aload_0
       9: getfield      #73                 // Field adpanel:Ljavax/swing/JPanel;
      12: aload_1
      13: invokevirtual #61                 // Method javax/swing/JPanel.add:(Ljava/awt/Component;)Ljava/awt/Component;
      16: pop
      17: aload_0
      18: getfield      #73                 // Field adpanel:Ljavax/swing/JPanel;
      21: iconst_1
      22: invokevirtual #120                // Method javax/swing/JPanel.setVisible:(Z)V
      25: aload_1
      26: invokevirtual #121                // Method LogoAnimatorJPanel.startAnimation:()V
      29: aload_1
      30: aload_0
      31: invokevirtual #122                // Method LogoAnimatorJPanel.addMouseListener:(Ljava/awt/event/MouseListener;)V
      34: return

  public void getchoice();
    Code:
       0: new           #54                 // class javax/swing/JPanel
       3: dup
       4: invokespecial #55                 // Method javax/swing/JPanel."<init>":()V
       7: astore_1
       8: aload_1
       9: aload_0
      10: getfield      #70                 // Field blo:Ljava/awt/BorderLayout;
      13: invokevirtual #59                 // Method javax/swing/JPanel.setLayout:(Ljava/awt/LayoutManager;)V
      16: new           #123                // class java/lang/StringBuilder
      19: dup
      20: invokespecial #124                // Method java/lang/StringBuilder."<init>":()V
      23: ldc           #125                // String                      W E L C O M E
      25: invokevirtual #126                // Method java/lang/StringBuilder.append:(Ljava/lang/String;)Ljava/lang/StringBuilder;
      28: aload_0
      29: getfield      #127                // Field user:Ljava/lang/String;
      32: invokevirtual #126                // Method java/lang/StringBuilder.append:(Ljava/lang/String;)Ljava/lang/StringBuilder;
      35: ldc           #128                // String  \n
      37: invokevirtual #126                // Method java/lang/StringBuilder.append:(Ljava/lang/String;)Ljava/lang/StringBuilder;
      40: ldc           #129                // String              \tPlease select your account \n
      42: invokevirtual #126                // Method java/lang/StringBuilder.append:(Ljava/lang/String;)Ljava/lang/StringBuilder;
      45: ldc           #130                // String          \t -------------------------------------------\n
      47: invokevirtual #126                // Method java/lang/StringBuilder.append:(Ljava/lang/String;)Ljava/lang/StringBuilder;
      50: invokevirtual #131                // Method java/lang/StringBuilder.toString:()Ljava/lang/String;
      53: astore_2
      54: new           #95                 // class javax/swing/JTextArea
      57: dup
      58: aload_2
      59: invokespecial #96                 // Method javax/swing/JTextArea."<init>":(Ljava/lang/String;)V
      62: astore_3
      63: aload_3
      64: aload_0
      65: getfield      #92                 // Field c1:Ljava/awt/Color;
      68: invokevirtual #97                 // Method javax/swing/JTextArea.setBackground:(Ljava/awt/Color;)V
      71: aload_3
      72: iconst_0
      73: invokevirtual #98                 // Method javax/swing/JTextArea.setEditable:(Z)V
      76: aload_1
      77: aload_3
      78: aload_0
      79: getfield      #70                 // Field blo:Ljava/awt/BorderLayout;
      82: pop
      83: ldc           #99                 // String North
      85: invokevirtual #78                 // Method javax/swing/JPanel.add:(Ljava/awt/Component;Ljava/lang/Object;)V
      88: new           #54                 // class javax/swing/JPanel
      91: dup
      92: invokespecial #55                 // Method javax/swing/JPanel."<init>":()V
      95: astore        4
      97: aload         4
      99: new           #57                 // class java/awt/GridLayout
     102: dup
     103: iconst_2
     104: iconst_1
     105: bipush        30
     107: bipush        40
     109: invokespecial #58                 // Method java/awt/GridLayout."<init>":(IIII)V
     112: invokevirtual #59                 // Method javax/swing/JPanel.setLayout:(Ljava/awt/LayoutManager;)V
     115: new           #100                // class javax/swing/JLabel
     118: dup
     119: ldc           #132                // String SAVING
     121: invokespecial #102                // Method javax/swing/JLabel."<init>":(Ljava/lang/String;)V
     124: astore        5
     126: new           #100                // class javax/swing/JLabel
     129: dup
     130: ldc           #133                // String CURRENT
     132: invokespecial #102                // Method javax/swing/JLabel."<init>":(Ljava/lang/String;)V
     135: astore        6
     137: aload         4
     139: aload         5
     141: invokevirtual #61                 // Method javax/swing/JPanel.add:(Ljava/awt/Component;)Ljava/awt/Component;
     144: pop
     145: aload         4
     147: aload         6
     149: invokevirtual #61                 // Method javax/swing/JPanel.add:(Ljava/awt/Component;)Ljava/awt/Component;
     152: pop
     153: aload_1
     154: aload         4
     156: aload_0
     157: getfield      #70                 // Field blo:Ljava/awt/BorderLayout;
     160: pop
     161: ldc           #115                // String East
     163: invokevirtual #78                 // Method javax/swing/JPanel.add:(Ljava/awt/Component;Ljava/lang/Object;)V
     166: aload_0
     167: getfield      #75                 // Field mainpanel:Ljavax/swing/JPanel;
     170: aload_1
     171: invokevirtual #61                 // Method javax/swing/JPanel.add:(Ljava/awt/Component;)Ljava/awt/Component;
     174: pop
     175: aload_0
     176: getfield      #26                 // Field but5:Ljavax/swing/JButton;
     179: aload_0
     180: invokevirtual #117                // Method javax/swing/JButton.addActionListener:(Ljava/awt/event/ActionListener;)V
     183: aload_0
     184: getfield      #27                 // Field but6:Ljavax/swing/JButton;
     187: aload_0
     188: invokevirtual #117                // Method javax/swing/JButton.addActionListener:(Ljava/awt/event/ActionListener;)V
     191: return

  public void getaccountscreen();
    Code:
       0: aload_0
       1: new           #65                 // class java/awt/CardLayout
       4: dup
       5: invokespecial #66                 // Method java/awt/CardLayout."<init>":()V
       8: putfield      #134                // Field cardlay1:Ljava/awt/CardLayout;
      11: aload_0
      12: getfield      #76                 // Field accountpanel:Ljavax/swing/JPanel;
      15: aload_0
      16: getfield      #92                 // Field c1:Ljava/awt/Color;
      19: invokevirtual #64                 // Method javax/swing/JPanel.setBackground:(Ljava/awt/Color;)V
      22: aload_0
      23: getfield      #76                 // Field accountpanel:Ljavax/swing/JPanel;
      26: aload_0
      27: getfield      #134                // Field cardlay1:Ljava/awt/CardLayout;
      30: invokevirtual #59                 // Method javax/swing/JPanel.setLayout:(Ljava/awt/LayoutManager;)V
      33: aload_0
      34: new           #54                 // class javax/swing/JPanel
      37: dup
      38: invokespecial #55                 // Method javax/swing/JPanel."<init>":()V
      41: putfield      #135                // Field options:Ljavax/swing/JPanel;
      44: aload_0
      45: new           #54                 // class javax/swing/JPanel
      48: dup
      49: invokespecial #55                 // Method javax/swing/JPanel."<init>":()V
      52: putfield      #136                // Field enquiry:Ljavax/swing/JPanel;
      55: aload_0
      56: new           #54                 // class javax/swing/JPanel
      59: dup
      60: invokespecial #55                 // Method javax/swing/JPanel."<init>":()V
      63: putfield      #137                // Field fastpanel:Ljavax/swing/JPanel;
      66: aload_0
      67: new           #54                 // class javax/swing/JPanel
      70: dup
      71: invokespecial #55                 // Method javax/swing/JPanel."<init>":()V
      74: putfield      #138                // Field withdrawal:Ljavax/swing/JPanel;
      77: aload_0
      78: new           #54                 // class javax/swing/JPanel
      81: dup
      82: invokespecial #55                 // Method javax/swing/JPanel."<init>":()V
      85: putfield      #139                // Field withdrawal1:Ljavax/swing/JPanel;
      88: aload_0
      89: new           #54                 // class javax/swing/JPanel
      92: dup
      93: invokespecial #55                 // Method javax/swing/JPanel."<init>":()V
      96: putfield      #140                // Field ministatement:Ljavax/swing/JPanel;
      99: aload_0
     100: new           #54                 // class javax/swing/JPanel
     103: dup
     104: invokespecial #55                 // Method javax/swing/JPanel."<init>":()V
     107: putfield      #141                // Field depositpanel:Ljavax/swing/JPanel;
     110: aload_0
     111: new           #54                 // class javax/swing/JPanel
     114: dup
     115: invokespecial #55                 // Method javax/swing/JPanel."<init>":()V
     118: putfield      #142                // Field transferpanel:Ljavax/swing/JPanel;
     121: aload_0
     122: new           #54                 // class javax/swing/JPanel
     125: dup
     126: invokespecial #55                 // Method javax/swing/JPanel."<init>":()V
     129: putfield      #143                // Field transferpanel1:Ljavax/swing/JPanel;
     132: aload_0
     133: new           #54                 // class javax/swing/JPanel
     136: dup
     137: invokespecial #55                 // Method javax/swing/JPanel."<init>":()V
     140: putfield      #144                // Field exit:Ljavax/swing/JPanel;
     143: ldc           #145                // String   \n \nFAST CASH\t\t\tBALANCE ENQUIRY \n                                 \n  \nCASH WITHDRAWAL\t\tDEPOSIT \n \t\t\t\t\t\t\n\t\n MINI STATEMENT\t\tTRANSFER
     145: astore_1
     146: new           #95                 // class javax/swing/JTextArea
     149: dup
     150: aload_1
     151: invokespecial #96                 // Method javax/swing/JTextArea."<init>":(Ljava/lang/String;)V
     154: astore_2
     155: aload_2
     156: aload_0
     157: getfield      #92                 // Field c1:Ljava/awt/Color;
     160: invokevirtual #97                 // Method javax/swing/JTextArea.setBackground:(Ljava/awt/Color;)V
     163: aload_2
     164: iconst_0
     165: invokevirtual #98                 // Method javax/swing/JTextArea.setEditable:(Z)V
     168: aload_0
     169: getfield      #135                // Field options:Ljavax/swing/JPanel;
     172: aload_2
     173: invokevirtual #61                 // Method javax/swing/JPanel.add:(Ljava/awt/Component;)Ljava/awt/Component;
     176: pop
     177: new           #123                // class java/lang/StringBuilder
     180: dup
     181: invokespecial #124                // Method java/lang/StringBuilder."<init>":()V
     184: ldc           #146                // String \n\n\n  Dear
     186: invokevirtual #126                // Method java/lang/StringBuilder.append:(Ljava/lang/String;)Ljava/lang/StringBuilder;
     189: aload_0
     190: getfield      #127                // Field user:Ljava/lang/String;
     193: invokevirtual #126                // Method java/lang/StringBuilder.append:(Ljava/lang/String;)Ljava/lang/StringBuilder;
     196: ldc           #147                // String \n Select your choice
     198: invokevirtual #126                // Method java/lang/StringBuilder.append:(Ljava/lang/String;)Ljava/lang/StringBuilder;
     201: ldc           #148                // String \n   on your Account NO
     203: invokevirtual #126                // Method java/lang/StringBuilder.append:(Ljava/lang/String;)Ljava/lang/StringBuilder;
     206: aload_0
     207: getfield      #149                // Field accno:I
     210: invokevirtual #150                // Method java/lang/StringBuilder.append:(I)Ljava/lang/StringBuilder;
     213: invokevirtual #131                // Method java/lang/StringBuilder.toString:()Ljava/lang/String;
     216: astore_3
     217: new           #95                 // class javax/swing/JTextArea
     220: dup
     221: aload_3
     222: invokespecial #96                 // Method javax/swing/JTextArea."<init>":(Ljava/lang/String;)V
     225: astore        4
     227: aload         4
     229: aload_0
     230: getfield      #92                 // Field c1:Ljava/awt/Color;
     233: invokevirtual #97                 // Method javax/swing/JTextArea.setBackground:(Ljava/awt/Color;)V
     236: aload         4
     238: iconst_0
     239: invokevirtual #98                 // Method javax/swing/JTextArea.setEditable:(Z)V
     242: aload_0
     243: getfield      #135                // Field options:Ljavax/swing/JPanel;
     246: aload         4
     248: invokevirtual #61                 // Method javax/swing/JPanel.add:(Ljava/awt/Component;)Ljava/awt/Component;
     251: pop
     252: aload_0
     253: getfield      #76                 // Field accountpanel:Ljavax/swing/JPanel;
     256: aload_0
     257: getfield      #135                // Field options:Ljavax/swing/JPanel;
     260: ldc           #151                // String options
     262: invokevirtual #78                 // Method javax/swing/JPanel.add:(Ljava/awt/Component;Ljava/lang/Object;)V
     265: aload_0
     266: getfield      #76                 // Field accountpanel:Ljavax/swing/JPanel;
     269: aload_0
     270: getfield      #136                // Field enquiry:Ljavax/swing/JPanel;
     273: ldc           #152                // String enquiry
     275: invokevirtual #78                 // Method javax/swing/JPanel.add:(Ljava/awt/Component;Ljava/lang/Object;)V
     278: aload_0
     279: getfield      #76                 // Field accountpanel:Ljavax/swing/JPanel;
     282: aload_0
     283: getfield      #137                // Field fastpanel:Ljavax/swing/JPanel;
     286: ldc           #153                // String fast
     288: invokevirtual #78                 // Method javax/swing/JPanel.add:(Ljava/awt/Component;Ljava/lang/Object;)V
     291: aload_0
     292: getfield      #76                 // Field accountpanel:Ljavax/swing/JPanel;
     295: aload_0
     296: getfield      #138                // Field withdrawal:Ljavax/swing/JPanel;
     299: ldc           #154                // String withdrawal
     301: invokevirtual #78                 // Method javax/swing/JPanel.add:(Ljava/awt/Component;Ljava/lang/Object;)V
     304: aload_0
     305: getfield      #76                 // Field accountpanel:Ljavax/swing/JPanel;
     308: aload_0
     309: getfield      #139                // Field withdrawal1:Ljavax/swing/JPanel;
     312: ldc           #155                // String withdrawal1
     314: invokevirtual #78                 // Method javax/swing/JPanel.add:(Ljava/awt/Component;Ljava/lang/Object;)V
     317: aload_0
     318: getfield      #76                 // Field accountpanel:Ljavax/swing/JPanel;
     321: aload_0
     322: getfield      #140                // Field ministatement:Ljavax/swing/JPanel;
     325: ldc           #156                // String ministatement
     327: invokevirtual #78                 // Method javax/swing/JPanel.add:(Ljava/awt/Component;Ljava/lang/Object;)V
     330: aload_0
     331: getfield      #76                 // Field accountpanel:Ljavax/swing/JPanel;
     334: aload_0
     335: getfield      #141                // Field depositpanel:Ljavax/swing/JPanel;
     338: ldc           #157                // String deposit
     340: invokevirtual #78                 // Method javax/swing/JPanel.add:(Ljava/awt/Component;Ljava/lang/Object;)V
     343: aload_0
     344: getfield      #76                 // Field accountpanel:Ljavax/swing/JPanel;
     347: aload_0
     348: getfield      #142                // Field transferpanel:Ljavax/swing/JPanel;
     351: ldc           #158                // String transfer
     353: invokevirtual #78                 // Method javax/swing/JPanel.add:(Ljava/awt/Component;Ljava/lang/Object;)V
     356: aload_0
     357: getfield      #76                 // Field accountpanel:Ljavax/swing/JPanel;
     360: aload_0
     361: getfield      #143                // Field transferpanel1:Ljavax/swing/JPanel;
     364: ldc           #159                // String transfer1
     366: invokevirtual #78                 // Method javax/swing/JPanel.add:(Ljava/awt/Component;Ljava/lang/Object;)V
     369: aload_0
     370: getfield      #76                 // Field accountpanel:Ljavax/swing/JPanel;
     373: aload_0
     374: getfield      #144                // Field exit:Ljavax/swing/JPanel;
     377: ldc           #160                // String exit
     379: invokevirtual #78                 // Method javax/swing/JPanel.add:(Ljava/awt/Component;Ljava/lang/Object;)V
     382: aload_0
     383: getfield      #135                // Field options:Ljavax/swing/JPanel;
     386: aload_0
     387: getfield      #92                 // Field c1:Ljava/awt/Color;
     390: invokevirtual #64                 // Method javax/swing/JPanel.setBackground:(Ljava/awt/Color;)V
     393: aload_0
     394: getfield      #134                // Field cardlay1:Ljava/awt/CardLayout;
     397: aload_0
     398: getfield      #76                 // Field accountpanel:Ljavax/swing/JPanel;
     401: ldc           #151                // String options
     403: invokevirtual #161                // Method java/awt/CardLayout.show:(Ljava/awt/Container;Ljava/lang/String;)V
     406: getstatic     #162                // Field java/lang/System.out:Ljava/io/PrintStream;
     409: ldc           #163                // String start
     411: invokevirtual #164                // Method java/io/PrintStream.println:(Ljava/lang/String;)V
     414: getstatic     #162                // Field java/lang/System.out:Ljava/io/PrintStream;
     417: getstatic     #165                // Field cnt6:I
     420: invokevirtual #166                // Method java/io/PrintStream.println:(I)V
     423: aload_0
     424: getfield      #14                 // Field but1:Ljavax/swing/JButton;
     427: aload_0
     428: getfield      #8                  // Field handler:LAtm$OptionButtonHandler;
     431: invokevirtual #117                // Method javax/swing/JButton.addActionListener:(Ljava/awt/event/ActionListener;)V
     434: aload_0
     435: getfield      #22                 // Field but2:Ljavax/swing/JButton;
     438: aload_0
     439: getfield      #8                  // Field handler:LAtm$OptionButtonHandler;
     442: invokevirtual #117                // Method javax/swing/JButton.addActionListener:(Ljava/awt/event/ActionListener;)V
     445: aload_0
     446: getfield      #23                 // Field but3:Ljavax/swing/JButton;
     449: aload_0
     450: getfield      #8                  // Field handler:LAtm$OptionButtonHandler;
     453: invokevirtual #117                // Method javax/swing/JButton.addActionListener:(Ljava/awt/event/ActionListener;)V
     456: aload_0
     457: getfield      #25                 // Field but4:Ljavax/swing/JButton;
     460: aload_0
     461: getfield      #8                  // Field handler:LAtm$OptionButtonHandler;
     464: invokevirtual #117                // Method javax/swing/JButton.addActionListener:(Ljava/awt/event/ActionListener;)V
     467: aload_0
     468: getfield      #26                 // Field but5:Ljavax/swing/JButton;
     471: aload_0
     472: getfield      #8                  // Field handler:LAtm$OptionButtonHandler;
     475: invokevirtual #117                // Method javax/swing/JButton.addActionListener:(Ljava/awt/event/ActionListener;)V
     478: aload_0
     479: getfield      #27                 // Field but6:Ljavax/swing/JButton;
     482: aload_0
     483: getfield      #8                  // Field handler:LAtm$OptionButtonHandler;
     486: invokevirtual #117                // Method javax/swing/JButton.addActionListener:(Ljava/awt/event/ActionListener;)V
     489: return

  public void gettransfer();
    Code:
       0: new           #100                // class javax/swing/JLabel
       3: dup
       4: ldc           #167                // String \t\tOK\t
       6: invokespecial #102                // Method javax/swing/JLabel."<init>":(Ljava/lang/String;)V
       9: astore_1
      10: new           #100                // class javax/swing/JLabel
      13: dup
      14: ldc           #168                // String  \tEnter the account no
      16: invokespecial #102                // Method javax/swing/JLabel."<init>":(Ljava/lang/String;)V
      19: astore_2
      20: new           #100                // class javax/swing/JLabel
      23: dup
      24: ldc           #169                // String  \tEnter the amount
      26: invokespecial #102                // Method javax/swing/JLabel."<init>":(Ljava/lang/String;)V
      29: astore_3
      30: aload_0
      31: new           #104                // class javax/swing/JTextField
      34: dup
      35: iconst_4
      36: invokespecial #105                // Method javax/swing/JTextField."<init>":(I)V
      39: putfield      #170                // Field textamt:Ljavax/swing/JTextField;
      42: aload_0
      43: new           #104                // class javax/swing/JTextField
      46: dup
      47: iconst_4
      48: invokespecial #105                // Method javax/swing/JTextField."<init>":(I)V
      51: putfield      #171                // Field textamt1:Ljavax/swing/JTextField;
      54: new           #54                 // class javax/swing/JPanel
      57: dup
      58: invokespecial #55                 // Method javax/swing/JPanel."<init>":()V
      61: astore        4
      63: aload         4
      65: new           #172                // class java/awt/FlowLayout
      68: dup
      69: bipush        50
      71: invokespecial #173                // Method java/awt/FlowLayout."<init>":(I)V
      74: invokevirtual #59                 // Method javax/swing/JPanel.setLayout:(Ljava/awt/LayoutManager;)V
      77: aload         4
      79: aload_0
      80: getfield      #93                 // Field c2:Ljava/awt/Color;
      83: invokevirtual #64                 // Method javax/swing/JPanel.setBackground:(Ljava/awt/Color;)V
      86: aload         4
      88: aload_2
      89: invokevirtual #61                 // Method javax/swing/JPanel.add:(Ljava/awt/Component;)Ljava/awt/Component;
      92: pop
      93: aload         4
      95: aload_0
      96: getfield      #170                // Field textamt:Ljavax/swing/JTextField;
      99: invokevirtual #61                 // Method javax/swing/JPanel.add:(Ljava/awt/Component;)Ljava/awt/Component;
     102: pop
     103: aload         4
     105: aload_3
     106: invokevirtual #61                 // Method javax/swing/JPanel.add:(Ljava/awt/Component;)Ljava/awt/Component;
     109: pop
     110: aload         4
     112: aload_0
     113: getfield      #171                // Field textamt1:Ljavax/swing/JTextField;
     116: invokevirtual #61                 // Method javax/swing/JPanel.add:(Ljava/awt/Component;)Ljava/awt/Component;
     119: pop
     120: aload         4
     122: aload_1
     123: invokevirtual #61                 // Method javax/swing/JPanel.add:(Ljava/awt/Component;)Ljava/awt/Component;
     126: pop
     127: aload_0
     128: getfield      #142                // Field transferpanel:Ljavax/swing/JPanel;
     131: aload         4
     133: aload_0
     134: getfield      #70                 // Field blo:Ljava/awt/BorderLayout;
     137: pop
     138: ldc           #115                // String East
     140: invokevirtual #78                 // Method javax/swing/JPanel.add:(Ljava/awt/Component;Ljava/lang/Object;)V
     143: aload_0
     144: getfield      #170                // Field textamt:Ljavax/swing/JTextField;
     147: invokevirtual #116                // Method javax/swing/JTextField.requestFocus:()V
     150: iconst_1
     151: putstatic     #174                // Field keystate:I
     154: aload_0
     155: invokevirtual #175                // Method initkeypad:()V
     158: return

  public void printmini();
    Code:
       0: new           #176                // class Query
       3: dup
       4: invokespecial #177                // Method Query."<init>":()V
       7: astore_1
       8: bipush        10
      10: anewarray     #178                // class java/lang/String
      13: astore_2
      14: aload_1
      15: aload_0
      16: getfield      #149                // Field accno:I
      19: invokevirtual #179                // Method Query.ministatement:(I)[Ljava/lang/String;
      22: astore_2
      23: aconst_null
      24: aload_2
      25: invokestatic  #180                // Method javax/swing/JOptionPane.showMessageDialog:(Ljava/awt/Component;Ljava/lang/Object;)V
      28: return

  public void getfastpanel();
    Code:
       0: aload_0
       1: getfield      #137                // Field fastpanel:Ljavax/swing/JPanel;
       4: aload_0
       5: getfield      #92                 // Field c1:Ljava/awt/Color;
       8: invokevirtual #64                 // Method javax/swing/JPanel.setBackground:(Ljava/awt/Color;)V
      11: ldc           #181                // String   \n \nINR 100\t\t    \tINR 500 \n                                 \n  \nINR 1000\t\t    \tINR 5000 \n \t\t\t\t\t\t\n\t\n INR 10000\t     \t\tINR 15000
      13: astore_1
      14: new           #95                 // class javax/swing/JTextArea
      17: dup
      18: aload_1
      19: invokespecial #96                 // Method javax/swing/JTextArea."<init>":(Ljava/lang/String;)V
      22: astore_2
      23: aload_2
      24: aload_0
      25: getfield      #92                 // Field c1:Ljava/awt/Color;
      28: invokevirtual #97                 // Method javax/swing/JTextArea.setBackground:(Ljava/awt/Color;)V
      31: aload_2
      32: iconst_0
      33: invokevirtual #98                 // Method javax/swing/JTextArea.setEditable:(Z)V
      36: aload_0
      37: getfield      #137                // Field fastpanel:Ljavax/swing/JPanel;
      40: aload_2
      41: invokevirtual #61                 // Method javax/swing/JPanel.add:(Ljava/awt/Component;)Ljava/awt/Component;
      44: pop
      45: new           #123                // class java/lang/StringBuilder
      48: dup
      49: invokespecial #124                // Method java/lang/StringBuilder."<init>":()V
      52: ldc           #146                // String \n\n\n  Dear
      54: invokevirtual #126                // Method java/lang/StringBuilder.append:(Ljava/lang/String;)Ljava/lang/StringBuilder;
      57: aload_0
      58: getfield      #127                // Field user:Ljava/lang/String;
      61: invokevirtual #126                // Method java/lang/StringBuilder.append:(Ljava/lang/String;)Ljava/lang/StringBuilder;
      64: ldc           #182                // String \n Select your option
      66: invokevirtual #126                // Method java/lang/StringBuilder.append:(Ljava/lang/String;)Ljava/lang/StringBuilder;
      69: invokevirtual #131                // Method java/lang/StringBuilder.toString:()Ljava/lang/String;
      72: astore_3
      73: new           #95                 // class javax/swing/JTextArea
      76: dup
      77: aload_3
      78: invokespecial #96                 // Method javax/swing/JTextArea."<init>":(Ljava/lang/String;)V
      81: astore        4
      83: aload         4
      85: aload_0
      86: getfield      #92                 // Field c1:Ljava/awt/Color;
      89: invokevirtual #97                 // Method javax/swing/JTextArea.setBackground:(Ljava/awt/Color;)V
      92: aload         4
      94: iconst_0
      95: invokevirtual #98                 // Method javax/swing/JTextArea.setEditable:(Z)V
      98: aload_0
      99: getfield      #137                // Field fastpanel:Ljavax/swing/JPanel;
     102: aload         4
     104: invokevirtual #61                 // Method javax/swing/JPanel.add:(Ljava/awt/Component;)Ljava/awt/Component;
     107: pop
     108: return

  public void showWithrawalOptions();
    Code:
       0: new           #100                // class javax/swing/JLabel
       3: dup
       4: ldc           #167                // String \t\tOK\t
       6: invokespecial #102                // Method javax/swing/JLabel."<init>":(Ljava/lang/String;)V
       9: astore_1
      10: new           #100                // class javax/swing/JLabel
      13: dup
      14: ldc           #169                // String  \tEnter the amount
      16: invokespecial #102                // Method javax/swing/JLabel."<init>":(Ljava/lang/String;)V
      19: astore_2
      20: aload_0
      21: new           #104                // class javax/swing/JTextField
      24: dup
      25: iconst_4
      26: invokespecial #105                // Method javax/swing/JTextField."<init>":(I)V
      29: putfield      #170                // Field textamt:Ljavax/swing/JTextField;
      32: new           #54                 // class javax/swing/JPanel
      35: dup
      36: invokespecial #55                 // Method javax/swing/JPanel."<init>":()V
      39: astore_3
      40: aload_3
      41: new           #172                // class java/awt/FlowLayout
      44: dup
      45: bipush        50
      47: invokespecial #173                // Method java/awt/FlowLayout."<init>":(I)V
      50: invokevirtual #59                 // Method javax/swing/JPanel.setLayout:(Ljava/awt/LayoutManager;)V
      53: aload_3
      54: aload_0
      55: getfield      #93                 // Field c2:Ljava/awt/Color;
      58: invokevirtual #64                 // Method javax/swing/JPanel.setBackground:(Ljava/awt/Color;)V
      61: aload_3
      62: aload_2
      63: invokevirtual #61                 // Method javax/swing/JPanel.add:(Ljava/awt/Component;)Ljava/awt/Component;
      66: pop
      67: aload_3
      68: aload_0
      69: getfield      #170                // Field textamt:Ljavax/swing/JTextField;
      72: invokevirtual #61                 // Method javax/swing/JPanel.add:(Ljava/awt/Component;)Ljava/awt/Component;
      75: pop
      76: aload_3
      77: aload_1
      78: invokevirtual #61                 // Method javax/swing/JPanel.add:(Ljava/awt/Component;)Ljava/awt/Component;
      81: pop
      82: aload_0
      83: getfield      #138                // Field withdrawal:Ljavax/swing/JPanel;
      86: aload_3
      87: aload_0
      88: getfield      #70                 // Field blo:Ljava/awt/BorderLayout;
      91: pop
      92: ldc           #115                // String East
      94: invokevirtual #78                 // Method javax/swing/JPanel.add:(Ljava/awt/Component;Ljava/lang/Object;)V
      97: aload_0
      98: getfield      #170                // Field textamt:Ljavax/swing/JTextField;
     101: invokevirtual #116                // Method javax/swing/JTextField.requestFocus:()V
     104: aload_0
     105: invokevirtual #175                // Method initkeypad:()V
     108: return

  public void initkeypad();
    Code:
       0: new           #183                // class Atm$KeyActionHandler
       3: dup
       4: aload_0
       5: aconst_null
       6: invokespecial #184                // Method Atm$KeyActionHandler."<init>":(LAtm;LAtm$1;)V
       9: astore_1
      10: aload_0
      11: getfield      #29                 // Field b1:Ljavax/swing/JButton;
      14: aload_1
      15: invokevirtual #117                // Method javax/swing/JButton.addActionListener:(Ljava/awt/event/ActionListener;)V
      18: aload_0
      19: getfield      #31                 // Field b2:Ljavax/swing/JButton;
      22: aload_1
      23: invokevirtual #117                // Method javax/swing/JButton.addActionListener:(Ljava/awt/event/ActionListener;)V
      26: aload_0
      27: getfield      #33                 // Field b3:Ljavax/swing/JButton;
      30: aload_1
      31: invokevirtual #117                // Method javax/swing/JButton.addActionListener:(Ljava/awt/event/ActionListener;)V
      34: aload_0
      35: getfield      #35                 // Field b4:Ljavax/swing/JButton;
      38: aload_1
      39: invokevirtual #117                // Method javax/swing/JButton.addActionListener:(Ljava/awt/event/ActionListener;)V
      42: aload_0
      43: getfield      #37                 // Field b5:Ljavax/swing/JButton;
      46: aload_1
      47: invokevirtual #117                // Method javax/swing/JButton.addActionListener:(Ljava/awt/event/ActionListener;)V
      50: aload_0
      51: getfield      #39                 // Field b6:Ljavax/swing/JButton;
      54: aload_1
      55: invokevirtual #117                // Method javax/swing/JButton.addActionListener:(Ljava/awt/event/ActionListener;)V
      58: aload_0
      59: getfield      #41                 // Field b7:Ljavax/swing/JButton;
      62: aload_1
      63: invokevirtual #117                // Method javax/swing/JButton.addActionListener:(Ljava/awt/event/ActionListener;)V
      66: aload_0
      67: getfield      #43                 // Field b8:Ljavax/swing/JButton;
      70: aload_1
      71: invokevirtual #117                // Method javax/swing/JButton.addActionListener:(Ljava/awt/event/ActionListener;)V
      74: aload_0
      75: getfield      #45                 // Field b9:Ljavax/swing/JButton;
      78: aload_1
      79: invokevirtual #117                // Method javax/swing/JButton.addActionListener:(Ljava/awt/event/ActionListener;)V
      82: aload_0
      83: getfield      #47                 // Field b0:Ljavax/swing/JButton;
      86: aload_1
      87: invokevirtual #117                // Method javax/swing/JButton.addActionListener:(Ljava/awt/event/ActionListener;)V
      90: aload_0
      91: getfield      #49                 // Field bclear:Ljavax/swing/JButton;
      94: aload_1
      95: invokevirtual #117                // Method javax/swing/JButton.addActionListener:(Ljava/awt/event/ActionListener;)V
      98: aload_0
      99: getfield      #51                 // Field bcancel:Ljavax/swing/JButton;
     102: aload_1
     103: invokevirtual #117                // Method javax/swing/JButton.addActionListener:(Ljava/awt/event/ActionListener;)V
     106: return

  public void showprintoptions();
    Code:
       0: new           #185                // class BalanceEnquiry
       3: dup
       4: aload_0
       5: getfield      #149                // Field accno:I
       8: invokespecial #186                // Method BalanceEnquiry."<init>":(I)V
      11: astore_1
      12: new           #68                 // class java/awt/BorderLayout
      15: dup
      16: invokespecial #69                 // Method java/awt/BorderLayout."<init>":()V
      19: astore_2
      20: aload_0
      21: getfield      #136                // Field enquiry:Ljavax/swing/JPanel;
      24: aload_2
      25: invokevirtual #59                 // Method javax/swing/JPanel.setLayout:(Ljava/awt/LayoutManager;)V
      28: new           #123                // class java/lang/StringBuilder
      31: dup
      32: invokespecial #124                // Method java/lang/StringBuilder."<init>":()V
      35: ldc           #187                // String \n\n\n\n\n  \t    ACCOUNT BALANCE  \n\t    Available balance :
      37: invokevirtual #126                // Method java/lang/StringBuilder.append:(Ljava/lang/String;)Ljava/lang/StringBuilder;
      40: aload_1
      41: getfield      #188                // Field BalanceEnquiry.abal:I
      44: invokevirtual #150                // Method java/lang/StringBuilder.append:(I)Ljava/lang/StringBuilder;
      47: ldc           #189                // String \n\t    Ledger    balance :
      49: invokevirtual #126                // Method java/lang/StringBuilder.append:(Ljava/lang/String;)Ljava/lang/StringBuilder;
      52: aload_1
      53: getfield      #190                // Field BalanceEnquiry.lbal:I
      56: invokevirtual #150                // Method java/lang/StringBuilder.append:(I)Ljava/lang/StringBuilder;
      59: ldc           #191                // String \n\n \t      Print statement
      61: invokevirtual #126                // Method java/lang/StringBuilder.append:(Ljava/lang/String;)Ljava/lang/StringBuilder;
      64: invokevirtual #131                // Method java/lang/StringBuilder.toString:()Ljava/lang/String;
      67: astore_3
      68: new           #95                 // class javax/swing/JTextArea
      71: dup
      72: aload_3
      73: invokespecial #96                 // Method javax/swing/JTextArea."<init>":(Ljava/lang/String;)V
      76: astore        4
      78: aload         4
      80: aload_0
      81: getfield      #92                 // Field c1:Ljava/awt/Color;
      84: invokevirtual #97                 // Method javax/swing/JTextArea.setBackground:(Ljava/awt/Color;)V
      87: aload         4
      89: iconst_0
      90: invokevirtual #98                 // Method javax/swing/JTextArea.setEditable:(Z)V
      93: aload_0
      94: getfield      #136                // Field enquiry:Ljavax/swing/JPanel;
      97: aload         4
      99: aload_2
     100: pop
     101: ldc           #192                // String Center
     103: invokevirtual #78                 // Method javax/swing/JPanel.add:(Ljava/awt/Component;Ljava/lang/Object;)V
     106: new           #54                 // class javax/swing/JPanel
     109: dup
     110: invokespecial #55                 // Method javax/swing/JPanel."<init>":()V
     113: astore        5
     115: aload         5
     117: new           #57                 // class java/awt/GridLayout
     120: dup
     121: iconst_4
     122: iconst_1
     123: bipush        10
     125: bipush        14
     127: invokespecial #58                 // Method java/awt/GridLayout."<init>":(IIII)V
     130: invokevirtual #59                 // Method javax/swing/JPanel.setLayout:(Ljava/awt/LayoutManager;)V
     133: aload         5
     135: aload_0
     136: getfield      #92                 // Field c1:Ljava/awt/Color;
     139: invokevirtual #64                 // Method javax/swing/JPanel.setBackground:(Ljava/awt/Color;)V
     142: new           #100                // class javax/swing/JLabel
     145: dup
     146: ldc           #193                // String \nYES
     148: invokespecial #102                // Method javax/swing/JLabel."<init>":(Ljava/lang/String;)V
     151: astore        6
     153: new           #100                // class javax/swing/JLabel
     156: dup
     157: ldc           #194                // String NO
     159: invokespecial #102                // Method javax/swing/JLabel."<init>":(Ljava/lang/String;)V
     162: astore        7
     164: aload         5
     166: aload         6
     168: invokevirtual #61                 // Method javax/swing/JPanel.add:(Ljava/awt/Component;)Ljava/awt/Component;
     171: pop
     172: aload         5
     174: aload         7
     176: invokevirtual #61                 // Method javax/swing/JPanel.add:(Ljava/awt/Component;)Ljava/awt/Component;
     179: pop
     180: aload_0
     181: getfield      #136                // Field enquiry:Ljavax/swing/JPanel;
     184: aload         5
     186: aload_2
     187: pop
     188: ldc           #115                // String East
     190: invokevirtual #78                 // Method javax/swing/JPanel.add:(Ljava/awt/Component;Ljava/lang/Object;)V
     193: return

  public void exitpanel();
    Code:
       0: new           #68                 // class java/awt/BorderLayout
       3: dup
       4: invokespecial #69                 // Method java/awt/BorderLayout."<init>":()V
       7: astore_1
       8: aload_0
       9: getfield      #144                // Field exit:Ljavax/swing/JPanel;
      12: aload_1
      13: invokevirtual #59                 // Method javax/swing/JPanel.setLayout:(Ljava/awt/LayoutManager;)V
      16: ldc           #195                // String \n\n\n\n\n \tDear User  \n\t    Thank You!!  \n\t    Symbiosis Computers Inc Ltd:\n\n \t      @ copywrites Parthav,Priyanka
      18: astore_2
      19: new           #95                 // class javax/swing/JTextArea
      22: dup
      23: aload_2
      24: invokespecial #96                 // Method javax/swing/JTextArea."<init>":(Ljava/lang/String;)V
      27: astore_3
      28: aload_3
      29: aload_0
      30: getfield      #92                 // Field c1:Ljava/awt/Color;
      33: invokevirtual #97                 // Method javax/swing/JTextArea.setBackground:(Ljava/awt/Color;)V
      36: aload_3
      37: iconst_0
      38: invokevirtual #98                 // Method javax/swing/JTextArea.setEditable:(Z)V
      41: aload_0
      42: getfield      #144                // Field exit:Ljavax/swing/JPanel;
      45: aload_3
      46: aload_1
      47: pop
      48: ldc           #192                // String Center
      50: invokevirtual #78                 // Method javax/swing/JPanel.add:(Ljava/awt/Component;Ljava/lang/Object;)V
      53: new           #54                 // class javax/swing/JPanel
      56: dup
      57: invokespecial #55                 // Method javax/swing/JPanel."<init>":()V
      60: astore        4
      62: aload         4
      64: new           #57                 // class java/awt/GridLayout
      67: dup
      68: iconst_4
      69: iconst_1
      70: bipush        10
      72: bipush        14
      74: invokespecial #58                 // Method java/awt/GridLayout."<init>":(IIII)V
      77: invokevirtual #59                 // Method javax/swing/JPanel.setLayout:(Ljava/awt/LayoutManager;)V
      80: aload         4
      82: aload_0
      83: getfield      #92                 // Field c1:Ljava/awt/Color;
      86: invokevirtual #64                 // Method javax/swing/JPanel.setBackground:(Ljava/awt/Color;)V
      89: new           #100                // class javax/swing/JLabel
      92: dup
      93: ldc           #196                // String \nEXIT
      95: invokespecial #102                // Method javax/swing/JLabel."<init>":(Ljava/lang/String;)V
      98: astore        5
     100: new           #100                // class javax/swing/JLabel
     103: dup
     104: ldc           #197                // String
     106: invokespecial #102                // Method javax/swing/JLabel."<init>":(Ljava/lang/String;)V
     109: astore        6
     111: aload         4
     113: aload         5
     115: invokevirtual #61                 // Method javax/swing/JPanel.add:(Ljava/awt/Component;)Ljava/awt/Component;
     118: pop
     119: aload         4
     121: aload         6
     123: invokevirtual #61                 // Method javax/swing/JPanel.add:(Ljava/awt/Component;)Ljava/awt/Component;
     126: pop
     127: aload_0
     128: getfield      #144                // Field exit:Ljavax/swing/JPanel;
     131: aload         4
     133: aload_1
     134: pop
     135: ldc           #115                // String East
     137: invokevirtual #78                 // Method javax/swing/JPanel.add:(Ljava/awt/Component;Ljava/lang/Object;)V
     140: return

  public void printslip();
    Code:
       0: new           #185                // class BalanceEnquiry
       3: dup
       4: aload_0
       5: getfield      #149                // Field accno:I
       8: invokespecial #186                // Method BalanceEnquiry."<init>":(I)V
      11: astore_1
      12: new           #198                // class java/util/Date
      15: dup
      16: invokespecial #199                // Method java/util/Date."<init>":()V
      19: astore_2
      20: new           #200                // class java/text/SimpleDateFormat
      23: dup
      24: ldc           #201                // String MM/dd/yyyy hh:mm:ss aaa
      26: invokespecial #202                // Method java/text/SimpleDateFormat."<init>":(Ljava/lang/String;)V
      29: astore_3
      30: aload_3
      31: aload_2
      32: invokevirtual #203                // Method java/text/SimpleDateFormat.format:(Ljava/util/Date;)Ljava/lang/String;
      35: astore        4
      37: new           #123                // class java/lang/StringBuilder
      40: dup
      41: invokespecial #124                // Method java/lang/StringBuilder."<init>":()V
      44: ldc           #204                // String \t\t  A/C NO :
      46: invokevirtual #126                // Method java/lang/StringBuilder.append:(Ljava/lang/String;)Ljava/lang/StringBuilder;
      49: aload_1
      50: getfield      #205                // Field BalanceEnquiry.accno:I
      53: invokevirtual #150                // Method java/lang/StringBuilder.append:(I)Ljava/lang/StringBuilder;
      56: ldc           #206                // String \n    Card no:
      58: invokevirtual #126                // Method java/lang/StringBuilder.append:(Ljava/lang/String;)Ljava/lang/StringBuilder;
      61: aload_0
      62: getfield      #207                // Field usr:I
      65: invokevirtual #150                // Method java/lang/StringBuilder.append:(I)Ljava/lang/StringBuilder;
      68: ldc           #208                // String \n\n
      70: invokevirtual #126                // Method java/lang/StringBuilder.append:(Ljava/lang/String;)Ljava/lang/StringBuilder;
      73: aload         4
      75: invokevirtual #126                // Method java/lang/StringBuilder.append:(Ljava/lang/String;)Ljava/lang/StringBuilder;
      78: ldc           #209                // String \n\n  Withdrawal :
      80: invokevirtual #126                // Method java/lang/StringBuilder.append:(Ljava/lang/String;)Ljava/lang/StringBuilder;
      83: getstatic     #210                // Field wd:I
      86: invokevirtual #150                // Method java/lang/StringBuilder.append:(I)Ljava/lang/StringBuilder;
      89: ldc           #211                // String \n\n  Available Balance:
      91: invokevirtual #126                // Method java/lang/StringBuilder.append:(Ljava/lang/String;)Ljava/lang/StringBuilder;
      94: aload_1
      95: getfield      #188                // Field BalanceEnquiry.abal:I
      98: invokevirtual #150                // Method java/lang/StringBuilder.append:(I)Ljava/lang/StringBuilder;
     101: ldc           #212                // String \n   Ledger Balance   :
     103: invokevirtual #126                // Method java/lang/StringBuilder.append:(Ljava/lang/String;)Ljava/lang/StringBuilder;
     106: aload_1
     107: getfield      #190                // Field BalanceEnquiry.lbal:I
     110: invokevirtual #150                // Method java/lang/StringBuilder.append:(I)Ljava/lang/StringBuilder;
     113: ldc           #213                // String \n\n  Thank you \n
     115: invokevirtual #126                // Method java/lang/StringBuilder.append:(Ljava/lang/String;)Ljava/lang/StringBuilder;
     118: ldc           #214                // String -------------------------------\n
     120: invokevirtual #126                // Method java/lang/StringBuilder.append:(Ljava/lang/String;)Ljava/lang/StringBuilder;
     123: invokevirtual #131                // Method java/lang/StringBuilder.toString:()Ljava/lang/String;
     126: astore        5
     128: aconst_null
     129: aload         5
     131: invokestatic  #180                // Method javax/swing/JOptionPane.showMessageDialog:(Ljava/awt/Component;Ljava/lang/Object;)V
     134: return

  public void printslipdeposit();
    Code:
       0: new           #185                // class BalanceEnquiry
       3: dup
       4: aload_0
       5: getfield      #149                // Field accno:I
       8: invokespecial #186                // Method BalanceEnquiry."<init>":(I)V
      11: astore_1
      12: new           #198                // class java/util/Date
      15: dup
      16: invokespecial #199                // Method java/util/Date."<init>":()V
      19: astore_2
      20: new           #200                // class java/text/SimpleDateFormat
      23: dup
      24: ldc           #201                // String MM/dd/yyyy hh:mm:ss aaa
      26: invokespecial #202                // Method java/text/SimpleDateFormat."<init>":(Ljava/lang/String;)V
      29: astore_3
      30: aload_3
      31: aload_2
      32: invokevirtual #203                // Method java/text/SimpleDateFormat.format:(Ljava/util/Date;)Ljava/lang/String;
      35: astore        4
      37: new           #123                // class java/lang/StringBuilder
      40: dup
      41: invokespecial #124                // Method java/lang/StringBuilder."<init>":()V
      44: ldc           #204                // String \t\t  A/C NO :
      46: invokevirtual #126                // Method java/lang/StringBuilder.append:(Ljava/lang/String;)Ljava/lang/StringBuilder;
      49: aload_1
      50: getfield      #205                // Field BalanceEnquiry.accno:I
      53: invokevirtual #150                // Method java/lang/StringBuilder.append:(I)Ljava/lang/StringBuilder;
      56: ldc           #206                // String \n    Card no:
      58: invokevirtual #126                // Method java/lang/StringBuilder.append:(Ljava/lang/String;)Ljava/lang/StringBuilder;
      61: aload_0
      62: getfield      #207                // Field usr:I
      65: invokevirtual #150                // Method java/lang/StringBuilder.append:(I)Ljava/lang/StringBuilder;
      68: ldc           #208                // String \n\n
      70: invokevirtual #126                // Method java/lang/StringBuilder.append:(Ljava/lang/String;)Ljava/lang/StringBuilder;
      73: aload         4
      75: invokevirtual #126                // Method java/lang/StringBuilder.append:(Ljava/lang/String;)Ljava/lang/StringBuilder;
      78: ldc           #215                // String \n\n  Deposit :
      80: invokevirtual #126                // Method java/lang/StringBuilder.append:(Ljava/lang/String;)Ljava/lang/StringBuilder;
      83: aload_0
      84: getfield      #216                // Field deposi:I
      87: invokevirtual #150                // Method java/lang/StringBuilder.append:(I)Ljava/lang/StringBuilder;
      90: ldc           #211                // String \n\n  Available Balance:
      92: invokevirtual #126                // Method java/lang/StringBuilder.append:(Ljava/lang/String;)Ljava/lang/StringBuilder;
      95: aload_1
      96: getfield      #188                // Field BalanceEnquiry.abal:I
      99: invokevirtual #150                // Method java/lang/StringBuilder.append:(I)Ljava/lang/StringBuilder;
     102: ldc           #212                // String \n   Ledger Balance   :
     104: invokevirtual #126                // Method java/lang/StringBuilder.append:(Ljava/lang/String;)Ljava/lang/StringBuilder;
     107: aload_1
     108: getfield      #190                // Field BalanceEnquiry.lbal:I
     111: invokevirtual #150                // Method java/lang/StringBuilder.append:(I)Ljava/lang/StringBuilder;
     114: ldc           #213                // String \n\n  Thank you \n
     116: invokevirtual #126                // Method java/lang/StringBuilder.append:(Ljava/lang/String;)Ljava/lang/StringBuilder;
     119: ldc           #214                // String -------------------------------\n
     121: invokevirtual #126                // Method java/lang/StringBuilder.append:(Ljava/lang/String;)Ljava/lang/StringBuilder;
     124: invokevirtual #131                // Method java/lang/StringBuilder.toString:()Ljava/lang/String;
     127: astore        5
     129: aconst_null
     130: aload         5
     132: invokestatic  #180                // Method javax/swing/JOptionPane.showMessageDialog:(Ljava/awt/Component;Ljava/lang/Object;)V
     135: return

  public void mouseClicked(java.awt.event.MouseEvent);
    Code:
       0: aload_0
       1: getfield      #67                 // Field cardlay:Ljava/awt/CardLayout;
       4: aload_0
       5: getfield      #71                 // Field panmiddle:Ljavax/swing/JPanel;
       8: ldc           #79                 // String login
      10: invokevirtual #161                // Method java/awt/CardLayout.show:(Ljava/awt/Container;Ljava/lang/String;)V
      13: aload_0
      14: invokevirtual #217                // Method Password:()V
      17: return

  public void mouseExited(java.awt.event.MouseEvent);
    Code:
       0: return

  public void mousePressed(java.awt.event.MouseEvent);
    Code:
       0: return

  public void mouseEntered(java.awt.event.MouseEvent);
    Code:
       0: return

  public void mouseReleased(java.awt.event.MouseEvent);
    Code:
       0: return

  public void actionPerformed(java.awt.event.ActionEvent);
    Code:
       0: aload_1
       1: invokevirtual #218                // Method java/awt/event/ActionEvent.getSource:()Ljava/lang/Object;
       4: aload_0
       5: getfield      #110                // Field but8:Ljavax/swing/JButton;
       8: if_acmpne     172
      11: new           #176                // class Query
      14: dup
      15: invokespecial #177                // Method Query."<init>":()V
      18: astore_2
      19: aload_0
      20: aload_0
      21: getfield      #106                // Field loginfield:Ljavax/swing/JTextField;
      24: invokevirtual #219                // Method javax/swing/JTextField.getText:()Ljava/lang/String;
      27: invokestatic  #220                // Method java/lang/Integer.parseInt:(Ljava/lang/String;)I
      30: putfield      #207                // Field usr:I
      33: aload_0
      34: aload_0
      35: getfield      #109                // Field pwordfield:Ljavax/swing/JPasswordField;
      38: invokevirtual #221                // Method javax/swing/JPasswordField.getText:()Ljava/lang/String;
      41: invokestatic  #220                // Method java/lang/Integer.parseInt:(Ljava/lang/String;)I
      44: putfield      #222                // Field pass:I
      47: aload_0
      48: aload_2
      49: aload_0
      50: getfield      #207                // Field usr:I
      53: aload_0
      54: getfield      #222                // Field pass:I
      57: invokevirtual #223                // Method Query.val_password:(II)Ljava/lang/String;
      60: putfield      #127                // Field user:Ljava/lang/String;
      63: aload_0
      64: getfield      #127                // Field user:Ljava/lang/String;
      67: ifnonnull     145
      70: aload_0
      71: dup
      72: getfield      #5                  // Field cnt:I
      75: iconst_1
      76: isub
      77: putfield      #5                  // Field cnt:I
      80: aload_0
      81: getfield      #5                  // Field cnt:I
      84: iflt          138
      87: aload_0
      88: getfield      #5                  // Field cnt:I
      91: iconst_1
      92: iadd
      93: istore_3
      94: aconst_null
      95: new           #123                // class java/lang/StringBuilder
      98: dup
      99: invokespecial #124                // Method java/lang/StringBuilder."<init>":()V
     102: ldc           #224                // String LOGIN ERROR!!\n You hav
     104: invokevirtual #126                // Method java/lang/StringBuilder.append:(Ljava/lang/String;)Ljava/lang/StringBuilder;
     107: iload_3
     108: invokevirtual #150                // Method java/lang/StringBuilder.append:(I)Ljava/lang/StringBuilder;
     111: ldc           #225                // String  chances left
     113: invokevirtual #126                // Method java/lang/StringBuilder.append:(Ljava/lang/String;)Ljava/lang/StringBuilder;
     116: invokevirtual #131                // Method java/lang/StringBuilder.toString:()Ljava/lang/String;
     119: invokestatic  #180                // Method javax/swing/JOptionPane.showMessageDialog:(Ljava/awt/Component;Ljava/lang/Object;)V
     122: aload_0
     123: getfield      #67                 // Field cardlay:Ljava/awt/CardLayout;
     126: aload_0
     127: getfield      #71                 // Field panmiddle:Ljavax/swing/JPanel;
     130: ldc           #79                 // String login
     132: invokevirtual #161                // Method java/awt/CardLayout.show:(Ljava/awt/Container;Ljava/lang/String;)V
     135: goto          172
     138: iconst_0
     139: invokestatic  #226                // Method java/lang/System.exit:(I)V
     142: goto          172
     145: getstatic     #162                // Field java/lang/System.out:Ljava/io/PrintStream;
     148: aload_0
     149: getfield      #127                // Field user:Ljava/lang/String;
     152: invokevirtual #164                // Method java/io/PrintStream.println:(Ljava/lang/String;)V
     155: aload_0
     156: getfield      #67                 // Field cardlay:Ljava/awt/CardLayout;
     159: aload_0
     160: getfield      #71                 // Field panmiddle:Ljavax/swing/JPanel;
     163: ldc           #80                 // String main
     165: invokevirtual #161                // Method java/awt/CardLayout.show:(Ljava/awt/Container;Ljava/lang/String;)V
     168: aload_0
     169: invokevirtual #227                // Method getchoice:()V
     172: aload_1
     173: invokevirtual #218                // Method java/awt/event/ActionEvent.getSource:()Ljava/lang/Object;
     176: aload_0
     177: getfield      #111                // Field but9:Ljavax/swing/JButton;
     180: if_acmpne     200
     183: aload_0
     184: getfield      #67                 // Field cardlay:Ljava/awt/CardLayout;
     187: aload_0
     188: getfield      #71                 // Field panmiddle:Ljavax/swing/JPanel;
     191: ldc           #77                 // String ad
     193: invokevirtual #161                // Method java/awt/CardLayout.show:(Ljava/awt/Container;Ljava/lang/String;)V
     196: aload_0
     197: invokevirtual #227                // Method getchoice:()V
     200: aload_1
     201: invokevirtual #218                // Method java/awt/event/ActionEvent.getSource:()Ljava/lang/Object;
     204: aload_0
     205: getfield      #26                 // Field but5:Ljavax/swing/JButton;
     208: if_acmpne     250
     211: aload_0
     212: getfield      #67                 // Field cardlay:Ljava/awt/CardLayout;
     215: aload_0
     216: getfield      #71                 // Field panmiddle:Ljavax/swing/JPanel;
     219: ldc           #81                 // String account
     221: invokevirtual #161                // Method java/awt/CardLayout.show:(Ljava/awt/Container;Ljava/lang/String;)V
     224: new           #176                // class Query
     227: dup
     228: invokespecial #177                // Method Query."<init>":()V
     231: astore_2
     232: aload_0
     233: aload_2
     234: aload_0
     235: getfield      #207                // Field usr:I
     238: ldc           #228                // String s
     240: invokevirtual #229                // Method Query.getacc:(ILjava/lang/String;)I
     243: putfield      #149                // Field accno:I
     246: aload_0
     247: invokevirtual #230                // Method getaccountscreen:()V
     250: aload_1
     251: invokevirtual #218                // Method java/awt/event/ActionEvent.getSource:()Ljava/lang/Object;
     254: aload_0
     255: getfield      #27                 // Field but6:Ljavax/swing/JButton;
     258: if_acmpne     300
     261: aload_0
     262: getfield      #67                 // Field cardlay:Ljava/awt/CardLayout;
     265: aload_0
     266: getfield      #71                 // Field panmiddle:Ljavax/swing/JPanel;
     269: ldc           #81                 // String account
     271: invokevirtual #161                // Method java/awt/CardLayout.show:(Ljava/awt/Container;Ljava/lang/String;)V
     274: new           #176                // class Query
     277: dup
     278: invokespecial #177                // Method Query."<init>":()V
     281: astore_2
     282: aload_0
     283: aload_2
     284: aload_0
     285: getfield      #207                // Field usr:I
     288: ldc           #231                // String c
     290: invokevirtual #229                // Method Query.getacc:(ILjava/lang/String;)I
     293: putfield      #149                // Field accno:I
     296: aload_0
     297: invokevirtual #230                // Method getaccountscreen:()V
     300: return

  public static void main(java.lang.String[]);
    Code:
       0: new           #232                // class Atm
       3: dup
       4: invokespecial #233                // Method "<init>":()V
       7: astore_1
       8: aload_1
       9: invokevirtual #234                // Method Atmmain:()V
      12: return

  static {};
    Code:
       0: iconst_1
       1: putstatic     #235                // Field z:I
       4: iconst_0
       5: putstatic     #210                // Field wd:I
       8: iconst_0
       9: putstatic     #174                // Field keystate:I
      12: iconst_0
      13: putstatic     #236                // Field cnt1:I
      16: iconst_0
      17: putstatic     #237                // Field cnt2:I
      20: iconst_0
      21: putstatic     #238                // Field cnt3:I
      24: iconst_0
      25: putstatic     #239                // Field cnt4:I
      28: iconst_0
      29: putstatic     #240                // Field cnt5:I
      32: iconst_0
      33: putstatic     #165                // Field cnt6:I
      36: return
}
